{
  "schema_version": 1,
  "name": "Terminal Glitch",
  "description": "駭客終端 — 極暗底色配高對比霓虹",
  "author": "cyberpunk-statusline",
  "colors": {
    "bg_primary": "#020312",
    "bg_panel": "#252A3F",
    "accent_1": "#24F0FF",
    "accent_2": "#FF5C8A",
    "accent_3": "#FFE45E",
    "warning": "#FFA03C",
    "alert": "#FF3232",
    "separator": "#444444",
    "dim": "#666666"
  },
  "symbols": {
    "nerd": {
      "model": "󰚩",
      "context": "󰍛",
      "rate_5h": "󰕐",
      "rate_7d": "󰔟",
      "directory": "󰉋",
      "git": "󰊢",
      "time": "󰅐",
      "bar_filled": "█",
      "bar_empty": "░"
    },
    "unicode": {
      "model": "⬡",
      "context": "◈",
      "rate_5h": "⚡",
      "rate_7d": "⟳",
      "directory": "⌁",
      "git": "⎇",
      "time": "◷",
      "bar_filled": "█",
      "bar_empty": "░"
    },
    "ascii": {
      "model": "[M]",
      "context": "[C]",
      "rate_5h": "[!]",
      "rate_7d": "[~]",
      "directory": "[D]",
      "git": "[G]",
      "time": "[T]",
      "bar_filled": "#",
      "bar_empty": "."
    }
  },
  "blocks": {
    "model": {
      "color": "accent_1",
      "bg": "bg_panel",
      "pl_bg": "accent_1",
      "pl_fg": "bg_primary"
    },
    "context": {
      "color": "accent_2",
      "bg": "bg_panel",
      "pl_bg": "accent_2",
      "pl_fg": "bg_primary"
    },
    "rate_5h": {
      "color": "accent_3",
      "bg": "bg_panel",
      "pl_bg": "accent_3",
      "pl_fg": "bg_primary"
    },
    "rate_7d": {
      "color": "accent_1",
      "bg": "bg_panel",
      "pl_bg": "accent_1",
      "pl_fg": "bg_primary"
    },
    "directory": {
      "color": "accent_2",
      "bg": "bg_panel",
      "pl_bg": "accent_2",
      "pl_fg": "bg_primary"
    },
    "git": {
      "color": "accent_1",
      "bg": "bg_panel",
      "pl_bg": "accent_3",
      "pl_fg": "bg_primary"
    },
    "time": {
      "color": "accent_1",
      "bg": "bg_primary",
      "pl_bg": "accent_1",
      "pl_fg": "bg_primary"
    }
  }
}
